admin_refresh/__init__.py
admin_refresh/apps.py
admin_refresh/static/admin/css/base.css
admin_refresh/static/admin/css/dark_mode.css
admin_refresh/static/admin/css/dashboard.css
admin_refresh/static/admin/css/nav_sidebar.css
admin_refresh/static/admin/css/responsive.css
admin_refresh/static/admin/js/SelectBox.js
admin_refresh/static/admin/js/SelectFilter2.js
admin_refresh/static/admin/js/actions.js
admin_refresh/static/admin/js/autocomplete.js
admin_refresh/static/admin/js/calendar.js
admin_refresh/static/admin/js/cancel.js
admin_refresh/static/admin/js/change_form.js
admin_refresh/static/admin/js/collapse.js
admin_refresh/static/admin/js/core.js
admin_refresh/static/admin/js/inlines.js
admin_refresh/static/admin/js/jquery.init.js
admin_refresh/static/admin/js/nav_sidebar.js
admin_refresh/static/admin/js/popup_response.js
admin_refresh/static/admin/js/prepopulate.js
admin_refresh/static/admin/js/prepopulate_init.js
admin_refresh/static/admin/js/urlify.js
admin_refresh/static/admin/js/admin/DateTimeShortcuts.js
admin_refresh/static/admin/js/admin/RelatedObjectLookups.js
admin_refresh/static/admin/js/vendor/jquery/LICENSE.txt
admin_refresh/static/admin/js/vendor/jquery/jquery.js
admin_refresh/static/admin/js/vendor/jquery/jquery.min.js
admin_refresh/static/admin/js/vendor/select2/LICENSE.md
admin_refresh/static/admin/js/vendor/select2/select2.full.js
admin_refresh/static/admin/js/vendor/select2/select2.full.min.js
admin_refresh/static/admin/js/vendor/select2/i18n/af.js
admin_refresh/static/admin/js/vendor/select2/i18n/ar.js
admin_refresh/static/admin/js/vendor/select2/i18n/az.js
admin_refresh/static/admin/js/vendor/select2/i18n/bg.js
admin_refresh/static/admin/js/vendor/select2/i18n/bn.js
admin_refresh/static/admin/js/vendor/select2/i18n/bs.js
admin_refresh/static/admin/js/vendor/select2/i18n/ca.js
admin_refresh/static/admin/js/vendor/select2/i18n/cs.js
admin_refresh/static/admin/js/vendor/select2/i18n/da.js
admin_refresh/static/admin/js/vendor/select2/i18n/de.js
django_admin_refresh-0.1.1.dist-info/LICENSE
django_admin_refresh-0.1.1.dist-info/METADATA
django_admin_refresh-0.1.1.dist-info/WHEEL
django_admin_refresh-0.1.1.dist-info/top_level.txt
django_admin_refresh-0.1.1.dist-info/RECORD
