Metadata-Version: 2.1
Name: django-admin-refresh
Version: 0.1.1
Summary: A refresh of the Django admin interface
Home-page: https://github.com/knyghty/django-admin-refresh
Author: Tom Carrick
Author-email: tom@carrick.eu
License: UNKNOWN
Platform: UNKNOWN
Classifier: Development Status :: 2 - Pre-Alpha
Classifier: Framework :: Django
Classifier: Intended Audience :: Developers
Classifier: License :: OSI Approved :: MIT License
Classifier: Operating System :: OS Independent
Classifier: Programming Language :: Python
Classifier: Programming Language :: Python :: 3
Classifier: Programming Language :: Python :: 3 :: Only
Classifier: Topic :: Internet :: WWW/HTTP
Requires-Python: >=3.8
License-File: LICENSE
Requires-Dist: Django
